{
  "code": "b5ee9c7201010101002300084202a9338ecd624ca15d37e4a8d9bf677ddc9b84f0e98f05f2fb84c7afe332a281b4",
  "code_hash": "ec614ea4aaea3f7768606f1c1632b3374d3de096a1e7c4ba43c8009c487fee9d",
  "methods": [
    {
      "id": 106029,
      "method": "get_jetton_data"
    },
    {
      "id": 81689,
      "method": "get_pool_data"
    },
    {
      "id": 82492,
      "method": "get_pool_type"
    },
    {
      "id": 87316,
      "method": "get_lp_account_address"
    },
    {
      "id": 103289,
      "method": "get_wallet_address"
    }
  ],
  "compiler": "func"
}